ros_pointcloud_recorder/__init__.py
ros_pointcloud_recorder/recorder.py
ros_pointcloud_recorder-0.1.4.dist-info/METADATA
ros_pointcloud_recorder-0.1.4.dist-info/WHEEL
ros_pointcloud_recorder-0.1.4.dist-info/entry_points.txt
ros_pointcloud_recorder-0.1.4.dist-info/top_level.txt
ros_pointcloud_recorder-0.1.4.dist-info/RECORD
