Metadata-Version: 2.1
Name: ros-pointcloud-recorder
Version: 0.1.4
Summary: ROS Point Cloud Recorder and Exporter
Home-page: https://github.com/Knighthood2001/ros-pointcloud-recorder
Author: knighthood2001
Author-email: 2109695291@qq.com
License: MIT
Keywords: ros pointcloud recorder pcl rosbag lidar
Platform: UNKNOWN
Classifier: Development Status :: 3 - Alpha
Classifier: Intended Audience :: Developers
Classifier: Intended Audience :: Science/Research
Classifier: License :: OSI Approved :: MIT License
Classifier: Programming Language :: Python :: 3
Classifier: Programming Language :: Python :: 3.6
Classifier: Programming Language :: Python :: 3.7
Classifier: Programming Language :: Python :: 3.8
Classifier: Programming Language :: Python :: 3.9
Classifier: Topic :: Scientific/Engineering
Classifier: Topic :: Software Development
Provides-Extra: dev
Requires-Dist: flake8 ; extra == 'dev'
Requires-Dist: pytest ; extra == 'dev'
